AUTHORS.md
CONTRIBUTING.md
HISTORY.md
LICENSE
MANIFEST.in
README.md
pyproject.toml
setup.cfg
setup.py
src/skidl/__init__.py
src/skidl/alias.py
src/skidl/bus.py
src/skidl/circuit.py
src/skidl/config_.py
src/skidl/design_class.py
src/skidl/erc.py
src/skidl/geometry.py
src/skidl/interface.py
src/skidl/logger.py
src/skidl/mixins.py
src/skidl/net.py
src/skidl/netlist_to_skidl.py
src/skidl/netpinlist.py
src/skidl/network.py
src/skidl/node.py
src/skidl/note.py
src/skidl/part.py
src/skidl/part_query.py
src/skidl/pckg_info.py
src/skidl/pin.py
src/skidl/pyspice.py
src/skidl/schlib.py
src/skidl/scriptinfo.py
src/skidl/skidl.py
src/skidl/skidlbaseobj.py
src/skidl/utilities.py
src/skidl.egg-info/PKG-INFO
src/skidl.egg-info/SOURCES.txt
src/skidl.egg-info/dependency_links.txt
src/skidl.egg-info/entry_points.txt
src/skidl.egg-info/not-zip-safe
src/skidl.egg-info/requires.txt
src/skidl.egg-info/top_level.txt
src/skidl/schematics/__init__.py
src/skidl/schematics/debug_draw.py
src/skidl/schematics/net_terminal.py
src/skidl/schematics/place.py
src/skidl/schematics/route.py
src/skidl/schematics/sch_node.py
src/skidl/scripts/__init__.py
src/skidl/scripts/netlist_to_skidl_main.py
src/skidl/scripts/part_search_cli.py
src/skidl/tools/__init__.py
src/skidl/tools/kicad5/__init__.py
src/skidl/tools/kicad5/bboxes.py
src/skidl/tools/kicad5/constants.py
src/skidl/tools/kicad5/draw_objs.py
src/skidl/tools/kicad5/gen_netlist.py
src/skidl/tools/kicad5/gen_pcb.py
src/skidl/tools/kicad5/gen_schematic.py
src/skidl/tools/kicad5/gen_svg.py
src/skidl/tools/kicad5/gen_xml.py
src/skidl/tools/kicad5/lib.py
src/skidl/tools/kicad6/__init__.py
src/skidl/tools/kicad6/bboxes.py
src/skidl/tools/kicad6/constants.py
src/skidl/tools/kicad6/gen_netlist.py
src/skidl/tools/kicad6/gen_pcb.py
src/skidl/tools/kicad6/gen_schematic.py
src/skidl/tools/kicad6/gen_svg.py
src/skidl/tools/kicad6/gen_xml.py
src/skidl/tools/kicad6/lib.py
src/skidl/tools/kicad7/__init__.py
src/skidl/tools/kicad7/bboxes.py
src/skidl/tools/kicad7/constants.py
src/skidl/tools/kicad7/gen_netlist.py
src/skidl/tools/kicad7/gen_pcb.py
src/skidl/tools/kicad7/gen_schematic.py
src/skidl/tools/kicad7/gen_svg.py
src/skidl/tools/kicad7/gen_xml.py
src/skidl/tools/kicad7/lib.py
