Metadata-Version: 2.4
Name: skidl
Version: 2.2.1
Summary: A Python package for textually describing electronic circuit schematics.
Home-page: https://github.com/devbisme/skidl
Author: Dave Vandenbout
Author-email: dave@vdb.name
License: MIT
Project-URL: Documentation, https://devbisme.github.io/skidl
Project-URL: Source, https://github.com/devbisme/skidl
Project-URL: Changelog, https://github.com/devbisme/skidl/blob/master/HISTORY.md
Project-URL: Tracker, https://github.com/devbisme/skidl/issues
Keywords: skidl kicad electronic circuit schematics
Classifier: Development Status :: 5 - Production/Stable
Classifier: Intended Audience :: Manufacturing
Classifier: License :: OSI Approved :: MIT License
Classifier: Natural Language :: English
Classifier: Operating System :: OS Independent
Classifier: Programming Language :: Python :: 3.6
Classifier: Programming Language :: Python :: 3.7
Classifier: Programming Language :: Python :: 3.8
Classifier: Programming Language :: Python :: 3.9
Classifier: Programming Language :: Python :: 3.10
Classifier: Programming Language :: Python :: 3.11
Classifier: Programming Language :: Python :: 3.12
Classifier: Programming Language :: Python :: 3.13
Classifier: Programming Language :: Python :: Implementation :: CPython
Classifier: Topic :: Scientific/Engineering :: Electronic Design Automation (EDA)
Requires-Python: >=3.6
License-File: LICENSE
License-File: AUTHORS.md
Requires-Dist: kinet2pcb>=1.1.4
Requires-Dist: simp_sexp>=0.3.0
Requires-Dist: inspice; python_version >= "3.11"
Requires-Dist: ply
Requires-Dist: rich
Requires-Dist: graphviz
Requires-Dist: deprecation
Dynamic: author
Dynamic: author-email
Dynamic: classifier
Dynamic: description
Dynamic: description-content-type
Dynamic: home-page
Dynamic: keywords
Dynamic: license
Dynamic: license-file
Dynamic: project-url
Dynamic: requires-dist
Dynamic: requires-python
Dynamic: summary
